nexuscosmos/__init__.py
nexuscosmos/acquisition.py
nexuscosmos/acquisition_base.py
nexuscosmos/cache.py
nexuscosmos/config.py
nexuscosmos/export.py
nexuscosmos/models.py
nexuscosmos/parsers.py
nexuscosmos/parsers_base.py
nexuscosmos/utils.py
nexuscosmos/datasets/__init__.py
nexuscosmos/datasets/horizons/__init__.py
nexuscosmos/datasets/horizons/client.py
nexuscosmos/datasets/horizons/parser.py
nexuscosmos-0.3.2.dist-info/licenses/LICENSE
nexuscosmos-0.3.2.dist-info/METADATA
nexuscosmos-0.3.2.dist-info/WHEEL
nexuscosmos-0.3.2.dist-info/top_level.txt
nexuscosmos-0.3.2.dist-info/RECORD
