Metadata-Version: 2.4
Name: nexuscosmos
Version: 0.3.2
Summary: A powerful, dataset-agnostic Python library for astronomical data acquisition with built-in caching, rate limiting, async support, and progress tracking
Author-email: Pancha Narayan Sahu <panchanarayansahu452@gmail.com>
License: MIT
Project-URL: Homepage, https://github.com/TheVishalKumar369/NexusComos
Project-URL: Documentation, https://github.com/TheVishalKumar369/NexusComos#readme
Project-URL: Repository, https://github.com/TheVishalKumar369/NexusComos.git
Project-URL: Issues, https://github.com/TheVishalKumar369/NexusComos/issues
Keywords: astronomy,ephemeris,orbital-mechanics,space,celestial,api-client,data-acquisition,caching,async,scientific-computing
Classifier: Development Status :: 4 - Beta
Classifier: Intended Audience :: Science/Research
Classifier: Intended Audience :: Developers
Classifier: License :: OSI Approved :: MIT License
Classifier: Programming Language :: Python :: 3
Classifier: Programming Language :: Python :: 3.8
Classifier: Programming Language :: Python :: 3.9
Classifier: Programming Language :: Python :: 3.10
Classifier: Programming Language :: Python :: 3.11
Classifier: Programming Language :: Python :: 3.12
Classifier: Topic :: Scientific/Engineering :: Astronomy
Classifier: Topic :: Scientific/Engineering :: Physics
Classifier: Topic :: Internet :: WWW/HTTP :: Dynamic Content
Requires-Python: >=3.8
License-File: LICENSE
Requires-Dist: requests>=2.28.0
Provides-Extra: astropy
Requires-Dist: astropy>=5.0; extra == "astropy"
Provides-Extra: pandas
Requires-Dist: pandas>=1.5.0; extra == "pandas"
Provides-Extra: async
Requires-Dist: aiohttp>=3.8.0; extra == "async"
Provides-Extra: progress
Requires-Dist: tqdm>=4.64.0; extra == "progress"
Provides-Extra: viz
Requires-Dist: matplotlib>=3.5.0; extra == "viz"
Requires-Dist: plotly>=5.0.0; extra == "viz"
Provides-Extra: dev
Requires-Dist: pytest>=7.0; extra == "dev"
Requires-Dist: pytest-cov>=4.0; extra == "dev"
Requires-Dist: black>=22.0; extra == "dev"
Requires-Dist: isort>=5.10; extra == "dev"
Requires-Dist: flake8>=4.0; extra == "dev"
Requires-Dist: mypy>=0.990; extra == "dev"
Provides-Extra: all
Requires-Dist: nexuscosmos[astropy,async,dev,pandas,progress,viz]; extra == "all"
Dynamic: license-file
